polars_ts-0.0.16.dist-info/METADATA
polars_ts-0.0.16.dist-info/WHEEL
polars_ts-0.0.16.dist-info/license_files/LICENSE
polars_ts/sf.py
polars_ts/mathx_helper/__init__.py
polars_ts/time.py
polars_ts/io_helper/__init__.py
polars_ts/futures_helper/bbg_symbols.py
polars_ts/futures_helper/util.py
polars_ts/futures_helper/__init__.py
polars_ts/futures_helper/generic_symbols.py
polars_ts/futures_helper/roll_calendar.py
polars_ts/param_schema.py
polars_ts/resample.py
polars_ts/dummymkt_helper/__init__.py
polars_ts/resample_helper/__init__.py
polars_ts/convert.py
polars_ts/io.py
polars_ts/time_helper/__init__.py
polars_ts/sf_helper/__init__.py
polars_ts/__init__.py
polars_ts/expr/sf.py
polars_ts/expr/time.py
polars_ts/expr/__init__.py
polars_ts/expr/random.py
polars_ts/expr/mathx.py
polars_ts/types.py
polars_ts/futures.py
polars_ts/display.py
polars_ts/calendar.py
polars_ts/calendar_helper/__init__.py
polars_ts/convert_helper/__init__.py
polars_ts/utils.py
polars_ts/mathx.py
polars_ts/grouper.py
polars_ts/dummymkt.py
polars_ts/dummy.py
polars_ts/report.py
polars_ts/tsf.py
polars_ts/dummy_helper/__init__.py
polars_ts/polars_ts.abi3.so
polars_ts-0.0.16.dist-info/RECORD
